basti_cdk/__init__.py
basti_cdk/py.typed
basti_cdk/_jsii/__init__.py
basti_cdk/_jsii/basti-cdk@1.1.1.jsii.tgz
basti_cdk-1.1.1.dist-info/LICENSE
basti_cdk-1.1.1.dist-info/METADATA
basti_cdk-1.1.1.dist-info/WHEEL
basti_cdk-1.1.1.dist-info/top_level.txt
basti_cdk-1.1.1.dist-info/RECORD
